tkscrollutil/CHANGES.txt
tkscrollutil/COPYRIGHT.txt
tkscrollutil/README.txt
tkscrollutil/__init__.py
tkscrollutil/attrib.py
tkscrollutil/load.py
tkscrollutil/pkgIndex.tcl
tkscrollutil/scrollableframe.py
tkscrollutil/scrollarea.py
tkscrollutil/scrollsync.py
tkscrollutil/scrollutil.tcl
tkscrollutil/scrollutilCommon.tcl
tkscrollutil/scrollutil_tile.tcl
tkscrollutil/ttk_scrollarea.py
tkscrollutil/ttk_scrollednotebook.py
tkscrollutil/ttk_scrollsync.py
tkscrollutil/wheelevent.py
tkscrollutil/scripts/__init__.py
tkscrollutil/scripts/attrib.tcl
tkscrollutil/scripts/notebookImages.tcl
tkscrollutil/scripts/pagesman.tcl
tkscrollutil/scripts/plainnotebook.tcl
tkscrollutil/scripts/scrollableframe.tcl
tkscrollutil/scripts/scrollarea.tcl
tkscrollutil/scripts/scrollednotebook.tcl
tkscrollutil/scripts/scrollsync.tcl
tkscrollutil/scripts/tclIndex
tkscrollutil/scripts/wheelEvent.tcl
tkscrollutil/scripts/utils/__init__.py
tkscrollutil/scripts/utils/mwutil.tcl
tkscrollutil/scripts/utils/pkgIndex.tcl
tkscrollutil/scripts/utils/scaleutil.tcl
tkscrollutil/scripts/utils/themepatch.tcl
tkscrollutil-1.3.117.dist-info/METADATA
tkscrollutil-1.3.117.dist-info/WHEEL
tkscrollutil-1.3.117.dist-info/top_level.txt
tkscrollutil-1.3.117.dist-info/RECORD
