Metadata-Version: 2.1
Name: tkscrollutil
Version: 1.3.117
Summary: tkinter scroll extra
Author: XiangQinxi
Author-email: XiangQinxi@outlook.com
Classifier: Programming Language :: Python :: 3
Classifier: License :: OSI Approved :: MIT License
Classifier: Operating System :: OS Independent
Requires-Python: >=3
